<?xml version="1.0" ?>
<!DOCTYPE bulletml SYSTEM "http://www.asahi-net.or.jp/~cs8k-cyu/bulletml/bulletml.dtd">

<!-- name is not part of the official bulletml xml spec, but can be used to give patterns proper names -->
<!-- or managing what type of bullets this particular patterns should be shooting --> 
<bulletml type="vertical"
          xmlns="http://www.asahi-net.or.jp/~cs8k-cyu/bulletml" name="yellow">  

<action label="top">

<repeat><times>100</times>
	<action>
		 <fire>
				<direction type="absolute">$rand</direction>
				<speed>1.2</speed>
				<bullet /> <!-- shoot the bullet! -->
		 </fire>
		<wait>0.7</wait>
			
		<fireRef label="test"> <!-- jump to label test below -->
			<param>17</param>
		</fireRef>
	</action>

</repeat>
</action>

<fire label="test">
	<bullet>
		<action>
			<fire>
				<direction type="sequence">$1</direction>
				<speed>0.2</speed>
				 <bullet/>
			</fire>
		</action>
	</bullet>
</fire>


</bulletml>
